odoo/addons/stock_warehouse_out_pull/README.rst
odoo/addons/stock_warehouse_out_pull/__init__.py
odoo/addons/stock_warehouse_out_pull/__manifest__.py
odoo/addons/stock_warehouse_out_pull/i18n/it.po
odoo/addons/stock_warehouse_out_pull/i18n/stock_warehouse_out_pull.pot
odoo/addons/stock_warehouse_out_pull/models/__init__.py
odoo/addons/stock_warehouse_out_pull/models/stock_warehouse.py
odoo/addons/stock_warehouse_out_pull/readme/CONFIGURE.md
odoo/addons/stock_warehouse_out_pull/readme/CONTRIBUTORS.md
odoo/addons/stock_warehouse_out_pull/readme/DESCRIPTION.md
odoo/addons/stock_warehouse_out_pull/static/description/icon.png
odoo/addons/stock_warehouse_out_pull/static/description/index.html
odoo/addons/stock_warehouse_out_pull/tests/__init__.py
odoo/addons/stock_warehouse_out_pull/tests/test_delivery_steps.py
odoo/addons/stock_warehouse_out_pull/views/stock_warehouse.xml
odoo_addon_stock_warehouse_out_pull-18.0.1.0.1.dist-info/METADATA
odoo_addon_stock_warehouse_out_pull-18.0.1.0.1.dist-info/WHEEL
odoo_addon_stock_warehouse_out_pull-18.0.1.0.1.dist-info/top_level.txt
odoo_addon_stock_warehouse_out_pull-18.0.1.0.1.dist-info/RECORD
