Metadata-Version: 2.1
Name: odoo-addon-stock_warehouse_out_pull
Version: 18.0.1.0.1
Requires-Python: >=3.10
Requires-Dist: odoo==18.0.*
Summary: Restore delivery pull rules as in Odoo <= 17.0
Home-page: https://github.com/OCA/stock-logistics-warehouse
License: LGPL-3
Author: Camptocamp, Odoo Community Association (OCA)
Author-email: support@odoo-community.org
Classifier: Programming Language :: Python
Classifier: Framework :: Odoo
Classifier: Framework :: Odoo :: 18.0
Classifier: License :: OSI Approved :: GNU Lesser General Public License v3 (LGPLv3)
